FoxDotLink/__init__.py
foxdotlink-0.1.0.dist-info/METADATA
foxdotlink-0.1.0.dist-info/WHEEL
foxdotlink-0.1.0.dist-info/licenses/LICENSE
foxdotlink-0.1.0.dist-info/RECORD
